{
  "project_info": {
    "project_number": "724662638750",
    "project_id": "e-commerce-2d807",
    "storage_bucket": "e-commerce-2d807.appspot.com"
  },
  "client": [
    {
      "client_info": {
        "mobilesdk_app_id": "1:724662638750:android:272874f5f15190ff39c38f",
        "android_client_info": {
          "package_name": "com.ecommerce"
        }
      },
      "oauth_client": [
        {
          "client_id": "724662638750-6vfduudse5hla26bjar98077hqdd746m.apps.googleusercontent.com",
          "client_type": 3
        }
      ],
      "api_key": [
        {
          "current_key": "AIzaSyAr83XGVt5lb2FoGDa0nPpfe9xxmavzPLs"
        }
      ],
      "services": {
        "appinvite_service": {
          "other_platform_oauth_client": [
            {
              "client_id": "724662638750-6vfduudse5hla26bjar98077hqdd746m.apps.googleusercontent.com",
              "client_type": 3
            }
          ]
        }
      }
    }
  ],
  "configuration_version": "1"
}